konachan_dl/__init__.py
konachan_dl/api.py
konachan_dl/const.py
konachan_dl/main.py
konachan_dl/stats.py
konachan_downloader-0.0.10.dist-info/licenses/LICENSE
konachan_downloader-0.0.10.dist-info/METADATA
konachan_downloader-0.0.10.dist-info/WHEEL
konachan_downloader-0.0.10.dist-info/entry_points.txt
konachan_downloader-0.0.10.dist-info/top_level.txt
konachan_downloader-0.0.10.dist-info/RECORD
