Metadata-Version: 2.4
Name: konachan-downloader
Version: 0.0.10
Summary: A professional, multi-threaded downloader for konachan.net
Author-email: Your Name <your.email@example.com>
Project-URL: Homepage, https://github.com/yourusername/konachan-downloader
Project-URL: Bug Tracker, https://github.com/yourusername/konachan-downloader/issues
Classifier: Programming Language :: Python :: 3
Classifier: License :: OSI Approved :: MIT License
Classifier: Operating System :: OS Independent
Requires-Python: >=3.8
License-File: LICENSE
Requires-Dist: requests
Requires-Dist: cloudscraper
Requires-Dist: tenacity
Requires-Dist: colorama
Requires-Dist: tqdm
Dynamic: license-file
